hwm/__init__.py
hwm/decorators.py
hwm/exceptions.py
hwm/metrics.py
hwm/api/__init__.py
hwm/api/property.py
hwm/compat/__init__.py
hwm/compat/sklearn.py
hwm/datasets/__init__.py
hwm/datasets/_datasets.py
hwm/estimators/__init__.py
hwm/estimators/_dynamic_system.py
hwm/estimators/dynamic_system.py
hwm/utils/__init__.py
hwm/utils/_array_api.py
hwm/utils/_core.py
hwm/utils/bunch.py
hwm/utils/context.py
hwm/utils/validator.py
hwm-1.1.4.dist-info/LICENSE
hwm-1.1.4.dist-info/METADATA
hwm-1.1.4.dist-info/WHEEL
hwm-1.1.4.dist-info/top_level.txt
hwm-1.1.4.dist-info/RECORD
