Metadata-Version: 2.1
Name: hwm
Version: 1.1.4
Summary: Adaptive Hammerstein-Wiener Modeling Toolkit
Home-page: https://github.com/earthai-tech/hwm
Download-URL: https://pypi.org/project/hwm/#files
Author: L.Kouadio
Author-email: etanoyau@gmail.com
Maintainer: L.Kouadio
Maintainer-email: etanoyau@gmail.com
License: BSD-3-Clause
Project-URL: API Documentation, https://hwm.readthedocs.io/en/stable/api.html
Project-URL: Home page, https://hwm.readthedocs.io
Project-URL: Bugs tracker, https://github.com/earthai-tech/hwm/issues
Project-URL: Installation guide, https://hwm.readthedocs.io/en/stable/installation.html
Project-URL: User guide, https://hwm.readthedocs.io/en/lateststable/user_guide.html
Keywords: machine learning,dynamic systems,algorithm,time series
Classifier: Development Status :: 3 - Alpha
Classifier: Intended Audience :: Science/Research
Classifier: Intended Audience :: Developers
Classifier: Topic :: Software Development
Classifier: Topic :: Scientific/Engineering
Classifier: Programming Language :: Python
Classifier: Programming Language :: Python :: 3.9
Classifier: Programming Language :: Python :: 3.10
Classifier: Programming Language :: Python :: 3.11
Classifier: Programming Language :: Python :: Implementation :: CPython
Classifier: Operating System :: OS Independent
Requires-Python: >=3.9
License-File: LICENSE
Requires-Dist: numpy<2
Requires-Dist: scipy>=1.7.0
Requires-Dist: scikit-learn>=1.2.0
Requires-Dist: pandas>=1.3.0
Provides-Extra: dev
Requires-Dist: pytest>=6.0.0; extra == "dev"
Requires-Dist: sphinx>=4.0.0; extra == "dev"
Requires-Dist: sphinx-rtd-theme; extra == "dev"
Requires-Dist: tensorflow>=2.6.0; extra == "dev"
Provides-Extra: examples
Requires-Dist: matplotlib>=3.4.0; extra == "examples"
Requires-Dist: tensorflow>=2.6.0; extra == "examples"
